PyResis/__init__.py
PyResis/cr.txt
PyResis/propulsion_power.py
PyResis-1.0.2.dist-info/DESCRIPTION.rst
PyResis-1.0.2.dist-info/METADATA
PyResis-1.0.2.dist-info/RECORD
PyResis-1.0.2.dist-info/WHEEL
PyResis-1.0.2.dist-info/metadata.json
PyResis-1.0.2.dist-info/top_level.txt
