Metadata-Version: 2.0
Name: PyResis
Version: 1.0.2
Summary: Python ship Resistance estimation package
Home-page: https://github.com/MaritimeRenewable/PyResis
Author: Yu Cao
Author-email: tsaoyu@gmail.com
License: MIT
Platform: UNKNOWN
